surehyp/__init__.py
surehyp/atmoCorrection.py
surehyp/preprocess.py
surehyp/various.py
surehyp-1.0.1.1.dist-info/LICENSE.txt
surehyp-1.0.1.1.dist-info/METADATA
surehyp-1.0.1.1.dist-info/WHEEL
surehyp-1.0.1.1.dist-info/top_level.txt
surehyp-1.0.1.1.dist-info/RECORD
