Metadata-Version: 2.1
Name: surehyp
Version: 1.0.1.1
Summary: This package was designed to obtain desmiled, destriped and georeferenced reflectance images from Hyperion imagery.
Author: Thomas Miraglio
Author-email: tmiragli@mail.ubc.ca
Project-URL: Bug Reports, https://github.com/tmiraglio/SUREHYP/issues
Project-URL: Source, https://github.com/tmiraglio/SUREHYP/
Keywords: hyperspectral,atmospheric correction,hyperion,remote sensing
Classifier: Development Status :: 5 - Production/Stable
Classifier: Topic :: Scientific/Engineering :: Image Processing
Classifier: License :: OSI Approved :: GNU General Public License v3 (GPLv3)
Classifier: Programming Language :: Python :: 3
Classifier: Programming Language :: Python :: 3.6
Classifier: Programming Language :: Python :: 3.7
Classifier: Programming Language :: Python :: 3.8
Classifier: Programming Language :: Python :: 3.9
Classifier: Programming Language :: Python :: 3 :: Only
Requires-Python: >=3.6, <3.10
License-File: LICENSE.txt
Requires-Dist: numpy
Requires-Dist: earthengine-api
Requires-Dist: geetools
Requires-Dist: matplotlib
Requires-Dist: spectral
Requires-Dist: scipy
Requires-Dist: pandas
Requires-Dist: opencv-python
Requires-Dist: scikit-learn
Requires-Dist: tqdm
